COPYING.txt
MANIFEST.in
NEWS.txt
README.txt
ez_setup.py
setup.py
src/trace2html.py
src/trace2htmldata/__init__.py
src/trace2htmldata/sortabletable.js
src/trace2htmldata/trace2html.css
trace2html.egg-info/PKG-INFO
trace2html.egg-info/SOURCES.txt
trace2html.egg-info/top_level.txt
