Metadata-Version: 1.0
Name: trace2html
Version: 0.2.1
Summary: HTML coverage report generator for trace.py
Home-page: http://champiland.homelinux.net/trace2html
Author: Olivier Grisel
Author-email: olivier.grisel@ensta.org
License: GNU GPL v2
Platform: UNKNOWN
Classifier: Development Status :: 4 - Beta
Classifier: Environment :: Console
Classifier: Intended Audience :: Developers
Classifier: License :: OSI Approved :: GNU General Public License (GPL)
Classifier: Operating System :: OS Independent
Classifier: Programming Language :: Python
